django_toon_rest/__init__.py
django_toon_rest/renderers.py
django_toon_rest-0.1.3.dist-info/licenses/LICENSE
tests/__init__.py
tests/settings.py
tests/test_renderers.py
django_toon_rest-0.1.3.dist-info/METADATA
django_toon_rest-0.1.3.dist-info/WHEEL
django_toon_rest-0.1.3.dist-info/top_level.txt
django_toon_rest-0.1.3.dist-info/RECORD
