Metadata-Version: 2.4
Name: django-toon-rest
Version: 0.1.3
Summary: Django REST Framework renderer for TOON format
Home-page: https://github.com/martinartaza/django-toon-rest
Author: Sebastian Martin Artaza Saade
Author-email: martin.artaza@gmail.com
License: MIT
Project-URL: Homepage, https://github.com/martinartaza/django-toon-rest
Project-URL: Author, https://www.sebastianartaza.com
Project-URL: Issue Tracker, https://github.com/martinartaza/django-toon-rest/issues
Classifier: Development Status :: 3 - Alpha
Classifier: Intended Audience :: Developers
Classifier: License :: OSI Approved :: MIT License
Classifier: Operating System :: OS Independent
Classifier: Programming Language :: Python :: 3
Classifier: Programming Language :: Python :: 3.8
Classifier: Programming Language :: Python :: 3.9
Classifier: Programming Language :: Python :: 3.10
Classifier: Programming Language :: Python :: 3.11
Classifier: Framework :: Django
Classifier: Framework :: Django :: 3.2
Classifier: Framework :: Django :: 4.0
Classifier: Framework :: Django :: 4.1
Classifier: Framework :: Django :: 4.2
Requires-Python: >=3.8
License-File: LICENSE
Requires-Dist: djangorestframework>=3.0.0
Requires-Dist: json-toon>=1.0.0
Dynamic: author
Dynamic: author-email
Dynamic: classifier
Dynamic: description
Dynamic: description-content-type
Dynamic: home-page
Dynamic: license
Dynamic: license-file
Dynamic: project-url
Dynamic: requires-dist
Dynamic: requires-python
Dynamic: summary
